<!DOCTYPE PATCH  SYSTEM "http://vvvv.org/versions/vvvv45beta31.2.dtd" >
   <PATCH nodename="E:\TekcorLivePerformance_Debug_16\Thirdparty\Monome App Test\Sequenze.v4p" filename="E:\TekcorLivePerformance_Debug_16\Thirdparty\Monome App Test\Sequenze.v4p" systemname="Sequenze">
   <BOUNDS height="11970" left="285" top="720" type="Window" width="17115">
   </BOUNDS>
   <NODE systemname="OSC_TransportIn (m4l receive)" filename="Modules\OSC_TransportIn (m4l receive).v4p" nodename="OSC_TransportIn (m4l receive)" componentmode="Hidden" id="64">
   <BOUNDS type="Node" left="8010" top="120" width="100" height="100">
   </BOUNDS>
   <BOUNDS type="Window" left="10395" top="3195" width="11970" height="8580">
   </BOUNDS>
   <PIN pinname="1/1 Bang" visible="1">
   </PIN>
   <PIN pinname="1/8 Bang" visible="1">
   </PIN>
   <PIN pinname="1/4 Bang" visible="1">
   </PIN>
   <PIN pinname="1/2 Bang" visible="1">
   </PIN>
   <PIN pinname="1/16 Bang" visible="1">
   </PIN>
   </NODE>
   <NODE systemname="MonomeInput" filename="MonomeInput.v4p" nodename="MonomeInput.v4p" componentmode="Hidden" id="65">
   <BOUNDS type="Node" left="3043" top="20" width="0" height="0">
   </BOUNDS>
   <BOUNDS type="Box" left="0" top="0" width="9330" height="7810">
   </BOUNDS>
   <BOUNDS type="Window" left="8293" top="2390" width="9330" height="7810">
   </BOUNDS>
   <PIN pinname="ROW COLUMN PRESS" visible="1">
   </PIN>
   <PIN pinname="Arguments" visible="1">
   </PIN>
   </NODE>
   <NODE systemname="Vector (3d Split)" nodename="Vector (3d Split)" componentmode="Hidden" id="68">
   <BOUNDS type="Node" left="4200" top="1245" width="100" height="100">
   </BOUNDS>
   <PIN pinname="XYZ" visible="1">
   </PIN>
   <PIN pinname="Y" visible="1">
   </PIN>
   <PIN pinname="Z" visible="1">
   </PIN>
   </NODE>
   <NODE nodename="IOBox (Value Advanced)" componentmode="InABox" id="69" systemname="IOBox (Value Advanced)">
   <BOUNDS type="Box" left="4200" top="1830" width="795" height="240">
   </BOUNDS>
   <BOUNDS type="Node" left="4200" top="1830" width="0" height="0">
   </BOUNDS>
   <PIN pinname="Units" slicecount="1" values="||">
   </PIN>
   <PIN pinname="Precision" slicecount="1" values="4">
   </PIN>
   <PIN pinname="Descriptive Name" slicecount="1" values="Row">
   </PIN>
   <PIN pinname="Y Output Value" visible="1">
   </PIN>
   </NODE>
   <LINK srcnodeid="68" srcpinname="X" dstnodeid="69" dstpinname="Y Input Value">
   </LINK>
   <NODE nodename="IOBox (Value Advanced)" componentmode="InABox" id="70" systemname="IOBox (Value Advanced)">
   <BOUNDS type="Box" left="5280" top="1890" width="795" height="240">
   </BOUNDS>
   <BOUNDS type="Node" left="5280" top="1890" width="0" height="0">
   </BOUNDS>
   <PIN pinname="Units" slicecount="1" values="||">
   </PIN>
   <PIN pinname="Precision" slicecount="1" values="4">
   </PIN>
   <PIN pinname="Descriptive Name" slicecount="1" values="Column">
   </PIN>
   <PIN pinname="Y Input Value" visible="1">
   </PIN>
   <PIN pinname="Y Output Value" visible="1">
   </PIN>
   </NODE>
   <NODE nodename="IOBox (Value Advanced)" componentmode="InABox" id="71" systemname="IOBox (Value Advanced)">
   <BOUNDS type="Box" left="6240" top="1965" width="795" height="240">
   </BOUNDS>
   <BOUNDS type="Node" left="6240" top="1965" width="0" height="0">
   </BOUNDS>
   <PIN pinname="Units" slicecount="1" values="||">
   </PIN>
   <PIN pinname="Precision" slicecount="1" values="4">
   </PIN>
   <PIN pinname="Descriptive Name" slicecount="1" values="Press">
   </PIN>
   <PIN pinname="Y Input Value" visible="1">
   </PIN>
   <PIN pinname="Y Output Value" visible="1">
   </PIN>
   </NODE>
   <LINK srcnodeid="68" srcpinname="Y" dstnodeid="70" dstpinname="Y Input Value">
   </LINK>
   <LINK srcnodeid="68" srcpinname="Z" dstnodeid="71" dstpinname="Y Input Value">
   </LINK>
   <NODE systemname="MonomeOutput" filename="MonomeOutput.v4p" nodename="MonomeOutput.v4p" componentmode="Hidden" id="89">
   <BOUNDS type="Node" left="2796" top="21217" width="0" height="0">
   </BOUNDS>
   <BOUNDS type="Box" left="1380" top="17955" width="8175" height="6525">
   </BOUNDS>
   <BOUNDS type="Window" left="9630" top="1470" width="11055" height="7815">
   </BOUNDS>
   <PIN pinname="Arguments" visible="1">
   </PIN>
   </NODE>
   <NODE systemname="IOBox (Value Advanced)" nodename="IOBox (Value Advanced)" componentmode="InABox" id="90">
   <BOUNDS type="Node" left="6090" top="16200" width="100" height="100">
   </BOUNDS>
   <BOUNDS type="Box" left="6090" top="16200" width="2085" height="885">
   </BOUNDS>
   <PIN pinname="Value Type" slicecount="1" values="Boolean">
   </PIN>
   <PIN pinname="Behavior" slicecount="1" values="Toggle">
   </PIN>
   <PIN pinname="Columns" slicecount="1" values="16">
   </PIN>
   <PIN pinname="Rows" slicecount="1" values="8">
   </PIN>
   <PIN pinname="SliceCount Mode" slicecount="1" values="ColsRowsPages">
   </PIN>
   <PIN pinname="Show Grid" slicecount="1" values="1">
   </PIN>
   <PIN pinname="X Input Value" slicecount="128" values="0,0,0,0,0,0,0,0,0,0,0,0,0,0,0,0,0,0,0,0,0,0,0,0,0,0,0,0,0,0,0,0,0,0,0,0,0,0,0,0,0,0,0,0,0,0,0,0,0,0,0,0,0,0,0,0,0,0,0,0,0,0,0,0,0,0,0,0,0,0,0,0,0,0,0,0,0,0,0,0,0,0,0,0,0,0,0,0,0,0,0,0,0,0,0,0,0,0,0,0,0,0,0,0,0,0,0,0,0,0,0,0,0,0,1,0,0,0,0,0,0,0,0,0,0,0,0,0">
   </PIN>
   <PIN pinname="Y Input Value" slicecount="128" visible="1" values="0,0,0,0,0,0,0,0,0,0,0,0,0,0,0,0,0,0,0,0,0,0,0,0,0,0,0,0,0,0,0,0,0,0,0,0,0,0,0,0,0,0,0,0,0,0,0,0,0,0,0,0,0,0,0,0,0,0,0,0,0,0,0,0,0,0,0,0,0,0,0,0,0,0,0,0,0,0,0,0,0,0,0,0,0,0,0,0,0,0,0,0,0,0,0,0,0,0,0,0,0,0,0,0,0,0,0,0,0,0,0,0,0,0,1,0,0,0,0,0,0,0,0,0,0,0,0,0">
   </PIN>
   <PIN pinname="Y Output Value" visible="1">
   </PIN>
   </NODE>
   <NODE systemname="IOBox (Value Advanced)" nodename="IOBox (Value Advanced)" componentmode="InABox" id="91">
   <BOUNDS type="Node" left="13035" top="15" width="100" height="100">
   </BOUNDS>
   <BOUNDS type="Box" left="13035" top="15" width="3495" height="2040">
   </BOUNDS>
   <PIN pinname="Value Type" slicecount="1" values="Boolean">
   </PIN>
   <PIN pinname="Behavior" slicecount="1" values="Toggle">
   </PIN>
   <PIN pinname="Columns" slicecount="1" values="16">
   </PIN>
   <PIN pinname="Rows" slicecount="1" values="8">
   </PIN>
   <PIN pinname="SliceCount Mode" slicecount="1" values="ColsRowsPages">
   </PIN>
   <PIN pinname="Show Grid" slicecount="1" values="1">
   </PIN>
   <PIN pinname="X Input Value" slicecount="128" values="0,0,0,0,0,0,0,0,0,0,0,0,0,0,0,0,0,0,0,0,0,0,0,0,0,0,0,0,0,0,0,0,0,0,0,0,0,0,0,0,0,0,0,0,0,0,0,0,0,0,0,0,0,0,0,0,0,0,0,0,0,0,0,0,0,0,0,0,0,0,0,0,0,0,0,0,0,0,0,0,0,0,0,0,0,0,0,0,0,0,0,0,0,0,0,0,0,0,0,0,0,0,0,0,0,0,0,0,0,0,0,0,0,0,0,0,0,0,0,0,0,0,0,0,0,0,0,0">
   </PIN>
   <PIN pinname="Y Input Value" slicecount="128" values="0,0,0,0,0,0,0,0,0,0,0,0,0,0,0,0,0,0,0,0,0,0,0,0,0,0,0,0,0,0,0,0,0,0,0,0,0,0,0,0,0,0,0,0,0,0,0,0,0,0,0,0,0,0,0,0,0,0,0,0,0,0,0,0,0,0,0,0,0,0,0,0,0,0,0,0,0,0,0,0,0,0,0,0,0,0,0,0,0,0,0,0,0,0,0,0,0,0,0,0,0,0,0,0,0,0,0,0,0,0,0,0,0,0,0,0,0,0,0,0,0,0,0,0,0,0,0,0">
   </PIN>
   <PIN pinname="Y Output Value" visible="1">
   </PIN>
   </NODE>
   <NODE systemname="Change (Animation)" nodename="Change (Animation)" componentmode="Hidden" id="92">
   <BOUNDS type="Node" left="6450" top="17310" width="100" height="100">
   </BOUNDS>
   <PIN pinname="Input" visible="1">
   </PIN>
   <PIN pinname="OnChange" visible="1">
   </PIN>
   </NODE>
   <LINK srcnodeid="90" srcpinname="Y Output Value" dstnodeid="92" dstpinname="Input">
   </LINK>
   <NODE systemname="I (Spreads)" nodename="I (Spreads)" componentmode="Hidden" id="95">
   <BOUNDS type="Node" left="3615" top="17910" width="100" height="100">
   </BOUNDS>
   <PIN pinname=".. To [" slicecount="1" values="16">
   </PIN>
   <PIN pinname="Output" visible="1">
   </PIN>
   </NODE>
   <NODE systemname="Select (Value)" nodename="Select (Value)" componentmode="Hidden" id="96">
   <BOUNDS type="Node" left="3630" top="18675" width="100" height="100">
   </BOUNDS>
   <PIN pinname="Index" visible="1">
   </PIN>
   <PIN pinname="Input" visible="1">
   </PIN>
   <PIN pinname="Select" visible="1">
   </PIN>
   <PIN pinname="Output" visible="1">
   </PIN>
   </NODE>
   <LINK srcnodeid="95" srcpinname="Output" dstnodeid="96" dstpinname="Input">
   </LINK>
   <NODE systemname="I (Spreads)" nodename="I (Spreads)" componentmode="Hidden" id="98">
   <BOUNDS type="Node" left="4785" top="17895" width="100" height="100">
   </BOUNDS>
   <PIN pinname=".. To [" slicecount="1" values="8">
   </PIN>
   <PIN pinname="Output" visible="1">
   </PIN>
   </NODE>
   <NODE systemname="Select (Value)" nodename="Select (Value)" componentmode="Hidden" id="99">
   <BOUNDS type="Node" left="4800" top="18255" width="100" height="100">
   </BOUNDS>
   <PIN pinname="Input" visible="1">
   </PIN>
   <PIN pinname="Select" visible="1">
   </PIN>
   <PIN pinname="Output" visible="1">
   </PIN>
   </NODE>
   <LINK srcnodeid="98" srcpinname="Output" dstnodeid="99" dstpinname="Input">
   </LINK>
   <NODE nodename="IOBox (Value Advanced)" componentmode="InABox" id="100" systemname="IOBox (Value Advanced)">
   <BOUNDS type="Box" left="15" top="15" width="795" height="240">
   </BOUNDS>
   <BOUNDS type="Node" left="15" top="15" width="0" height="0">
   </BOUNDS>
   <PIN pinname="Y Input Value" slicecount="1" values="16">
   </PIN>
   <PIN pinname="Units" slicecount="1" values="||">
   </PIN>
   <PIN pinname="Precision" slicecount="1" values="4">
   </PIN>
   <PIN pinname="Value Type" slicecount="1" values="Integer">
   </PIN>
   <PIN pinname="Y Output Value" visible="1">
   </PIN>
   <PIN pinname="Descriptive Name" slicecount="1" values="Columns">
   </PIN>
   </NODE>
   <LINK srcnodeid="100" srcpinname="Y Output Value" dstnodeid="95" dstpinname=".. To [" hiddenwhenlocked="1" linkstyle="Bezier">
   <LINKPOINT x="135" y="8193">
   </LINKPOINT>
   <LINKPOINT x="3735" y="9973">
   </LINKPOINT>
   </LINK>
   <LINK srcnodeid="100" srcpinname="Y Output Value" dstnodeid="99" dstpinname="Select" hiddenwhenlocked="1" linkstyle="Bezier">
   <LINKPOINT x="150" y="8365">
   </LINKPOINT>
   <LINKPOINT x="5205" y="10145">
   </LINKPOINT>
   </LINK>
   <NODE systemname="Select (Value)" nodename="Select (Value)" componentmode="Hidden" id="101">
   <BOUNDS type="Node" left="4800" top="18675" width="100" height="100">
   </BOUNDS>
   <PIN pinname="Index" visible="1">
   </PIN>
   <PIN pinname="Input" visible="1" slicecount="1" values="0">
   </PIN>
   <PIN pinname="Select" visible="1" slicecount="128" values="1">
   </PIN>
   <PIN pinname="Output" visible="1">
   </PIN>
   </NODE>
   <LINK srcnodeid="99" srcpinname="Output" dstnodeid="101" dstpinname="Input">
   </LINK>
   <NODE systemname="Select (Value)" nodename="Select (Value)" componentmode="Hidden" id="104">
   <BOUNDS type="Node" left="6060" top="18675" width="100" height="100">
   </BOUNDS>
   <PIN pinname="Index" visible="1">
   </PIN>
   <PIN pinname="Input" visible="1" slicecount="1" values="0">
   </PIN>
   <PIN pinname="Select" visible="1" slicecount="128" values="1">
   </PIN>
   <PIN pinname="Output" visible="1">
   </PIN>
   </NODE>
   <LINK srcnodeid="90" srcpinname="Y Output Value" dstnodeid="104" dstpinname="Input">
   </LINK>
   <NODE systemname="Vector (3d Join)" nodename="Vector (3d Join)" componentmode="Hidden" id="105">
   <BOUNDS type="Node" left="4065" top="19215" width="100" height="100">
   </BOUNDS>
   <PIN pinname="XYZ" visible="1">
   </PIN>
   <PIN pinname="X" visible="1" slicecount="2" values="0">
   </PIN>
   <PIN pinname="Z" slicecount="1" visible="1" values="1">
   </PIN>
   <PIN pinname="Y" visible="1">
   </PIN>
   </NODE>
   <LINK srcnodeid="104" srcpinname="Output" dstnodeid="105" dstpinname="Z">
   </LINK>
   <NODE nodename="IOBox (Value Advanced)" componentmode="InABox" id="116" systemname="IOBox (Value Advanced)">
   <BOUNDS type="Box" left="15" top="4440" width="285" height="240">
   </BOUNDS>
   <BOUNDS type="Node" left="15" top="4440" width="0" height="0">
   </BOUNDS>
   <PIN pinname="Y Input Value" slicecount="1" visible="1" values="0">
   </PIN>
   <PIN pinname="Units" slicecount="1" values="||">
   </PIN>
   <PIN pinname="Precision" slicecount="1" values="4">
   </PIN>
   <PIN pinname="Value Type" slicecount="1" values="Boolean">
   </PIN>
   <PIN pinname="Behavior" slicecount="1" values="Bang">
   </PIN>
   <PIN pinname="X Input Value" slicecount="1" values="0">
   </PIN>
   <PIN pinname="Descriptive Name" slicecount="1" values="||">
   </PIN>
   <PIN pinname="Y Output Value" visible="1">
   </PIN>
   </NODE>
   <LINK srcnodeid="116" srcpinname="Y Output Value" dstnodeid="89" dstpinname="Clear" hiddenwhenlocked="1">
   </LINK>
   <NODE nodename="IOBox (String)" componentmode="InABox" id="117" systemname="IOBox (String)">
   <BOUNDS type="Box" left="375" top="1920" width="915" height="255">
   </BOUNDS>
   <BOUNDS type="Node" left="375" top="1920" width="0" height="0">
   </BOUNDS>
   <PIN pinname="Input String" slicecount="1" values="example">
   </PIN>
   <PIN pinname="Default" slicecount="1" values="||">
   </PIN>
   <PIN pinname="File Mask" slicecount="1" values="||">
   </PIN>
   <PIN pinname="Maximum Characters" slicecount="1" values="-1">
   </PIN>
   <PIN pinname="Descriptive Name" slicecount="1" values="|Prefix without Backslash|">
   </PIN>
   </NODE>
   <LINK srcnodeid="117" srcpinname="Output String" dstnodeid="89" dstpinname="Prefix without Backslash" hiddenwhenlocked="1" linkstyle="Bezier">
   <LINKPOINT x="375" y="10823">
   </LINKPOINT>
   <LINKPOINT x="3480" y="12563">
   </LINKPOINT>
   </LINK>
   <LINK srcnodeid="96" srcpinname="Output" dstnodeid="105" dstpinname="X">
   </LINK>
   <LINK srcnodeid="101" srcpinname="Output" dstnodeid="105" dstpinname="Y">
   </LINK>
   <NODE systemname="FrameCounter (Animation)" nodename="FrameCounter (Animation)" componentmode="Hidden" id="122">
   <BOUNDS type="Node" left="4890" top="19950" width="100" height="100">
   </BOUNDS>
   <PIN pinname="Enable" slicecount="1" values="1">
   </PIN>
   <PIN pinname="Frame Count" visible="1">
   </PIN>
   </NODE>
   <NODE systemname="GetSlice (Spreads)" nodename="GetSlice (Spreads)" componentmode="Hidden" id="123">
   <BOUNDS type="Node" left="4065" top="20175" width="100" height="100">
   </BOUNDS>
   <PIN pinname="Index" visible="1">
   </PIN>
   <PIN pinname="Bin Size" slicecount="1" values="3">
   </PIN>
   <PIN pinname="Input" visible="1">
   </PIN>
   <PIN pinname="Output" visible="1">
   </PIN>
   </NODE>
   <LINK srcnodeid="122" srcpinname="Frame Count" dstnodeid="123" dstpinname="Index">
   </LINK>
   <NODE systemname="AsString (Value)" nodename="AsString (Value)" componentmode="Hidden" id="124">
   <BOUNDS type="Node" left="4065" top="20550" width="100" height="100">
   </BOUNDS>
   <PIN pinname="Output" visible="1">
   </PIN>
   <PIN pinname="Input" visible="1" slicecount="1" values="0">
   </PIN>
   <PIN pinname="SubType" slicecount="1" values="|Integer (0 .. MaxInt)|">
   </PIN>
   </NODE>
   <LINK srcnodeid="123" srcpinname="Output" dstnodeid="124" dstpinname="Input">
   </LINK>
   <NODE systemname="Queue (Spreads)" filename="%VVVV%\lib\nodes\plugins\VVVV.Nodes.dll" nodename="Queue (Spreads)" componentmode="Hidden" id="126">
   <BOUNDS type="Node" left="4050" top="19740" width="100" height="100">
   </BOUNDS>
   <PIN pinname="Input" visible="1" slicecount="1" values="0">
   </PIN>
   <PIN pinname="Output" visible="1">
   </PIN>
   <PIN pinname="Insert" slicecount="1" visible="1" values="0">
   </PIN>
   <PIN pinname="Frame Count" slicecount="1" values="1">
   </PIN>
   <PIN pinname="Reset" slicecount="1" values="0">
   </PIN>
   </NODE>
   <LINK srcnodeid="105" srcpinname="XYZ" dstnodeid="126" dstpinname="Input">
   </LINK>
   <LINK srcnodeid="126" srcpinname="Output" dstnodeid="123" dstpinname="Input">
   </LINK>
   <LINK srcnodeid="92" srcpinname="OnChange" dstnodeid="101" dstpinname="Select">
   </LINK>
   <LINK srcnodeid="92" srcpinname="OnChange" dstnodeid="96" dstpinname="Select">
   </LINK>
   <LINK srcnodeid="92" srcpinname="OnChange" dstnodeid="104" dstpinname="Select">
   </LINK>
   <NODE id="127" systemname="OR (Boolean Spectral)" nodename="OR (Boolean Spectral)" componentmode="Hidden" hiddenwhenlocked="0" managers="">
   <BOUNDS type="Node" left="6810" top="18705" width="100" height="100">
   </BOUNDS>
   <PIN pinname="Output" visible="1" pintype="Output">
   </PIN>
   <PIN pinname="Input" visible="1" pintype="Input">
   </PIN>
   <PIN pinname="Descriptive Name" pintype="Configuration" slicecount="1" values="||">
   </PIN>
   <PIN pinname="Bin Size" pintype="Input" visible="1" slicecount="1" values="-1">
   </PIN>
   <PIN pinname="ID" pintype="Output" visible="-1">
   </PIN>
   </NODE>
   <LINK srcnodeid="127" srcpinname="Output" dstnodeid="126" dstpinname="Insert">
   </LINK>
   <LINK srcnodeid="92" srcpinname="OnChange" dstnodeid="127" dstpinname="Input">
   </LINK>
   <NODE systemname="SetSlice (Spreads)" nodename="SetSlice (Spreads)" componentmode="Hidden" id="132">
   <BOUNDS type="Node" left="9450" top="4170" width="100" height="100">
   </BOUNDS>
   <PIN pinname="Index" visible="1" slicecount="1" values="0">
   </PIN>
   <PIN pinname="Input" slicecount="1" visible="1" values="1">
   </PIN>
   <PIN pinname="Output" visible="1">
   </PIN>
   <PIN pinname="Spread" visible="1" slicecount="1" values="0">
   </PIN>
   </NODE>
   <LINK srcnodeid="91" srcpinname="Y Output Value" dstnodeid="132" dstpinname="Spread" linkstyle="Bezier" hiddenwhenlocked="1">
   <LINKPOINT x="13475" y="3425">
   </LINKPOINT>
   <LINKPOINT x="9070" y="3325">
   </LINKPOINT>
   </LINK>
   <LINK srcnodeid="71" srcpinname="Y Output Value" dstnodeid="132" dstpinname="Input">
   </LINK>
   <NODE systemname="I (Spreads)" nodename="I (Spreads)" componentmode="Hidden" id="134">
   <BOUNDS type="Node" left="3990" top="2535" width="100" height="100">
   </BOUNDS>
   <PIN pinname=".. To [" slicecount="1" visible="1" values="8">
   </PIN>
   <PIN pinname="Output" visible="1">
   </PIN>
   <PIN pinname="[ From .." slicecount="1" values="0">
   </PIN>
   </NODE>
   <NODE systemname="Multiply (Value)" nodename="Multiply (Value)" componentmode="Hidden" id="135">
   <BOUNDS type="Node" left="4005" top="2985" width="100" height="100">
   </BOUNDS>
   <PIN pinname="Input 1" visible="1">
   </PIN>
   <PIN pinname="Input 2" visible="1">
   </PIN>
   <PIN pinname="Output" visible="1">
   </PIN>
   </NODE>
   <LINK srcnodeid="134" srcpinname="Output" dstnodeid="135" dstpinname="Input 1">
   </LINK>
   <LINK srcnodeid="100" srcpinname="Y Output Value" dstnodeid="135" dstpinname="Input 2" hiddenwhenlocked="1" linkstyle="Bezier">
   <LINKPOINT x="75" y="1605">
   </LINKPOINT>
   <LINKPOINT x="4275" y="1605">
   </LINKPOINT>
   </LINK>
   <NODE nodename="IOBox (Value Advanced)" componentmode="InABox" id="136" systemname="IOBox (Value Advanced)">
   <BOUNDS type="Box" left="15" top="510" width="795" height="240">
   </BOUNDS>
   <BOUNDS type="Node" left="15" top="510" width="0" height="0">
   </BOUNDS>
   <PIN pinname="Y Input Value" slicecount="1" values="8">
   </PIN>
   <PIN pinname="Units" slicecount="1" values="||">
   </PIN>
   <PIN pinname="Precision" slicecount="1" values="4">
   </PIN>
   <PIN pinname="Value Type" slicecount="1" values="Integer">
   </PIN>
   <PIN pinname="Y Output Value" visible="1">
   </PIN>
   <PIN pinname="Descriptive Name" slicecount="1" values="Rows">
   </PIN>
   </NODE>
   <LINK srcnodeid="136" srcpinname="Y Output Value" dstnodeid="98" dstpinname=".. To [" hiddenwhenlocked="1" linkstyle="Bezier">
   <LINKPOINT x="150" y="8433">
   </LINKPOINT>
   <LINKPOINT x="4905" y="10213">
   </LINKPOINT>
   </LINK>
   <NODE systemname="Add (Value)" nodename="Add (Value)" componentmode="Hidden" id="137">
   <BOUNDS type="Node" left="10035" top="3810" width="100" height="100">
   </BOUNDS>
   <PIN pinname="Input 1" visible="1">
   </PIN>
   <PIN pinname="Input 2" visible="1">
   </PIN>
   <PIN pinname="Output" visible="1">
   </PIN>
   </NODE>
   <NODE systemname="GetSlice (Spreads)" nodename="GetSlice (Spreads)" componentmode="Hidden" id="138">
   <BOUNDS type="Node" left="3990" top="3525" width="100" height="100">
   </BOUNDS>
   <PIN pinname="Input" visible="1">
   </PIN>
   <PIN pinname="Index" visible="1">
   </PIN>
   <PIN pinname="Output" visible="1">
   </PIN>
   </NODE>
   <LINK srcnodeid="135" srcpinname="Output" dstnodeid="138" dstpinname="Input" linkstyle="PolyLine">
   </LINK>
   <LINK srcnodeid="70" srcpinname="Y Output Value" dstnodeid="138" dstpinname="Index">
   </LINK>
   <LINK srcnodeid="138" srcpinname="Output" dstnodeid="137" dstpinname="Input 1">
   </LINK>
   <LINK srcnodeid="69" srcpinname="Y Output Value" dstnodeid="137" dstpinname="Input 2">
   </LINK>
   <LINK srcnodeid="137" srcpinname="Output" dstnodeid="132" dstpinname="Index">
   </LINK>
   <LINK srcnodeid="136" srcpinname="Y Output Value" dstnodeid="134" dstpinname=".. To [" hiddenwhenlocked="1" linkstyle="Bezier">
   <LINKPOINT x="75" y="1628">
   </LINKPOINT>
   <LINKPOINT x="4185" y="1628">
   </LINKPOINT>
   </LINK>
   <NODE nodename="IOBox (Value Advanced)" componentmode="InABox" id="151" systemname="IOBox (Value Advanced)">
   <BOUNDS type="Box" left="15" top="3765" width="795" height="240">
   </BOUNDS>
   <BOUNDS type="Node" left="15" top="3765" width="0" height="0">
   </BOUNDS>
   <PIN pinname="Y Input Value" slicecount="1" values="48">
   </PIN>
   <PIN pinname="Units" slicecount="1" values="||">
   </PIN>
   <PIN pinname="Precision" slicecount="1" values="4">
   </PIN>
   <PIN pinname="Value Type" slicecount="1" values="Integer">
   </PIN>
   <PIN pinname="Descriptive Name" slicecount="1" values="|Midi Note Offset|">
   </PIN>
   </NODE>
   <NODE systemname="MidiAllNotesOff (Devices)" filename="%VVVV%\lib\nodes\modules\Devices\MidiAllNotesOff (Devices).v4p" nodename="MidiAllNotesOff (Devices)" componentmode="Hidden" id="153">
   <BOUNDS type="Node" left="45" top="6000" width="100" height="100">
   </BOUNDS>
   <PIN pinname="Send" slicecount="1" visible="1" values="0">
   </PIN>
   <PIN pinname="Midi Output Port" slicecount="1" values="|LoopBe Internal MIDI|">
   </PIN>
   </NODE>
   <NODE systemname="MonoFlop (Animation)" nodename="MonoFlop (Animation)" componentmode="Hidden" id="160">
   <BOUNDS type="Node" left="8760" top="945" width="100" height="100">
   </BOUNDS>
   <PIN pinname="Set" visible="1">
   </PIN>
   <PIN pinname="Output" visible="1">
   </PIN>
   <PIN pinname="Time" slicecount="1" values="0.11">
   </PIN>
   </NODE>
   <LINK srcnodeid="64" srcpinname="1/2 Bang" dstnodeid="160" dstpinname="Set">
   </LINK>
   <NODE systemname="Switch (Value Input)" nodename="Switch (Value Input)" componentmode="Hidden" id="238">
   <BOUNDS type="Node" left="7875" top="1725" width="100" height="100">
   </BOUNDS>
   <PIN pinname="Input Count" slicecount="1" values="5">
   </PIN>
   <PIN pinname="Input 1" visible="1">
   </PIN>
   <PIN pinname="Input 2" visible="1">
   </PIN>
   <PIN pinname="Input 3" visible="1">
   </PIN>
   <PIN pinname="Input 4" visible="1">
   </PIN>
   <PIN pinname="Input 5" visible="1">
   </PIN>
   <PIN pinname="Output" visible="1">
   </PIN>
   <PIN pinname="Switch" visible="1">
   </PIN>
   </NODE>
   <LINK srcnodeid="64" srcpinname="1/1 Bang" dstnodeid="238" dstpinname="Input 1">
   </LINK>
   <LINK srcnodeid="64" srcpinname="1/2 Bang" dstnodeid="238" dstpinname="Input 2">
   </LINK>
   <LINK srcnodeid="64" srcpinname="1/4 Bang" dstnodeid="238" dstpinname="Input 3">
   </LINK>
   <LINK srcnodeid="64" srcpinname="1/8 Bang" dstnodeid="238" dstpinname="Input 4">
   </LINK>
   <LINK srcnodeid="64" srcpinname="1/16 Bang" dstnodeid="238" dstpinname="Input 5">
   </LINK>
   <NODE systemname="AvoidNIL (Spreads)" filename="%VVVV%\lib\nodes\modules\Spreads\AvoidNIL (Spreads).v4p" nodename="AvoidNIL (Spreads)" componentmode="Hidden" id="251">
   <BOUNDS type="Node" left="4200" top="585" width="100" height="100">
   </BOUNDS>
   <PIN pinname="Input" visible="1">
   </PIN>
   <PIN pinname="Output" visible="1">
   </PIN>
   </NODE>
   <LINK srcnodeid="65" srcpinname="ROW COLUMN PRESS" dstnodeid="251" dstpinname="Input">
   </LINK>
   <NODE systemname="AvoidNIL (String)" filename="%VVVV%\lib\nodes\modules\String\AvoidNIL (String).v4p" nodename="AvoidNIL (String)" componentmode="Hidden" id="252">
   <BOUNDS type="Node" left="4080" top="20895" width="100" height="100">
   </BOUNDS>
   <PIN pinname="Input" visible="1">
   </PIN>
   <PIN pinname="Output" visible="1">
   </PIN>
   </NODE>
   <LINK srcnodeid="124" srcpinname="Output" dstnodeid="252" dstpinname="Input">
   </LINK>
   <LINK srcnodeid="252" srcpinname="Output" dstnodeid="89" dstpinname="Arguments">
   </LINK>
   <NODE nodename="IOBox (Enumerations)" componentmode="InABox" id="253" systemname="IOBox (Enumerations)">
   <BOUNDS type="Box" left="15" top="2610" width="1590" height="240">
   </BOUNDS>
   <BOUNDS type="Node" left="15" top="2610" width="0" height="0">
   </BOUNDS>
   <PIN pinname="Input Enum" slicecount="1" values="|LoopBe Internal MIDI|">
   </PIN>
   <PIN pinname="Descriptive Name" slicecount="1" values="|Midi Output Port|">
   </PIN>
   </NODE>
   <NODE nodename="IOBox (Value Advanced)" componentmode="InABox" id="254" systemname="IOBox (Value Advanced)">
   <BOUNDS type="Box" left="15" top="3180" width="795" height="240">
   </BOUNDS>
   <BOUNDS type="Node" left="15" top="3180" width="0" height="0">
   </BOUNDS>
   <PIN pinname="Y Input Value" slicecount="1" values="0">
   </PIN>
   <PIN pinname="Units" slicecount="1" values="||">
   </PIN>
   <PIN pinname="Precision" slicecount="1" values="4">
   </PIN>
   <PIN pinname="Value Type" slicecount="1" values="Integer">
   </PIN>
   <PIN pinname="Descriptive Name" slicecount="1" values="Channel">
   </PIN>
   </NODE>
   <NODE nodename="IOBox (Value Advanced)" componentmode="InABox" id="260" systemname="IOBox (Value Advanced)">
   <BOUNDS type="Box" left="1740" top="315" width="795" height="240">
   </BOUNDS>
   <BOUNDS type="Node" left="1740" top="315" width="0" height="0">
   </BOUNDS>
   <PIN pinname="Y Input Value" slicecount="1" values="8001">
   </PIN>
   <PIN pinname="Units" slicecount="1" values="||">
   </PIN>
   <PIN pinname="Precision" slicecount="1" values="4">
   </PIN>
   <PIN pinname="Value Type" slicecount="1" values="Integer">
   </PIN>
   <PIN pinname="Descriptive Name" slicecount="1" values="|Local Port|">
   </PIN>
   </NODE>
   <LINK srcnodeid="260" srcpinname="Y Output Value" dstnodeid="65" dstpinname="Local Port">
   </LINK>
   <NODE systemname="MainLoop (VVVV)" nodename="MainLoop (VVVV)" componentmode="Hidden" id="-6">
   <BOUNDS type="Node" left="1455" top="3990" width="100" height="100">
   </BOUNDS>
   <PIN pinname="Maximum forground fps" slicecount="1" values="30">
   </PIN>
   <PIN pinname="Time Mode" slicecount="1" values="Filtered">
   </PIN>
   </NODE>
   <NODE systemname="PerfMeter (Debug)" filename="%VVVV%\lib\nodes\modules\Debug\PerfMeter (Debug).v4p" nodename="PerfMeter (Debug)" componentmode="Hidden" id="262">
   <BOUNDS type="Node" left="1995" top="4710" width="100" height="100">
   </BOUNDS>
   </NODE>
   <NODE nodename="IOBox (Value Advanced)" componentmode="InABox" id="263" systemname="IOBox (Value Advanced)">
   <BOUNDS type="Box" left="2550" top="5145" width="795" height="240">
   </BOUNDS>
   <BOUNDS type="Node" left="2550" top="5145" width="0" height="0">
   </BOUNDS>
   <PIN pinname="Units" slicecount="1" values="||">
   </PIN>
   <PIN pinname="Precision" slicecount="1" values="4">
   </PIN>
   </NODE>
   <LINK srcnodeid="262" srcpinname="fps" dstnodeid="263" dstpinname="Y Input Value">
   </LINK>
   <NODE systemname="MidiClock (Devices)" nodename="MidiClock (Devices)" componentmode="Hidden" id="264">
   <BOUNDS type="Node" left="5955" top="15" width="100" height="100">
   </BOUNDS>
   <PIN pinname="Enabled" slicecount="1" values="1">
   </PIN>
   <PIN pinname="Midi Input Port" slicecount="1" values="|LoopBe Internal MIDI|">
   </PIN>
   <PIN pinname="Beats per Measure" slicecount="1" values="1">
   </PIN>
   <PIN pinname="Beat Type" slicecount="1" visible="1" values="8">
   </PIN>
   </NODE>
   <NODE nodename="IOBox (Value Advanced)" componentmode="InABox" id="265" systemname="IOBox (Value Advanced)">
   <BOUNDS type="Box" left="6900" top="630" width="795" height="240">
   </BOUNDS>
   <BOUNDS type="Node" left="6900" top="630" width="0" height="0">
   </BOUNDS>
   <PIN pinname="Units" slicecount="1" values="||">
   </PIN>
   <PIN pinname="Precision" slicecount="1" values="4">
   </PIN>
   <PIN pinname="Value Type" slicecount="1" values="Integer">
   </PIN>
   <PIN pinname="Y Output Value" visible="1">
   </PIN>
   </NODE>
   <LINK srcnodeid="264" srcpinname="Measure" dstnodeid="265" dstpinname="Y Input Value">
   </LINK>
   <NODE nodename="IOBox (Value Advanced)" componentmode="InABox" id="266" systemname="IOBox (Value Advanced)">
   <BOUNDS type="Box" left="5940" top="660" width="795" height="240">
   </BOUNDS>
   <BOUNDS type="Node" left="5940" top="660" width="0" height="0">
   </BOUNDS>
   <PIN pinname="Units" slicecount="1" values="||">
   </PIN>
   <PIN pinname="Precision" slicecount="1" values="4">
   </PIN>
   </NODE>
   <LINK srcnodeid="264" srcpinname="Position in Measure" dstnodeid="266" dstpinname="Y Input Value">
   </LINK>
   <NODE systemname="Change (Animation)" nodename="Change (Animation)" componentmode="Hidden" id="267">
   <BOUNDS type="Node" left="6840" top="1200" width="100" height="100">
   </BOUNDS>
   <PIN pinname="Input" visible="1">
   </PIN>
   <PIN pinname="OnChange" visible="1">
   </PIN>
   </NODE>
   <LINK srcnodeid="265" srcpinname="Y Output Value" dstnodeid="267" dstpinname="Input">
   </LINK>
   <NODE systemname="Switch (Value Input)" nodename="Switch (Value Input)" componentmode="Hidden" id="268">
   <BOUNDS type="Node" left="6660" top="2895" width="100" height="100">
   </BOUNDS>
   <PIN pinname="Input 2" visible="1">
   </PIN>
   <PIN pinname="Input 1" visible="1">
   </PIN>
   <PIN pinname="Output" visible="1">
   </PIN>
   <PIN pinname="Input Count" slicecount="1" values="3">
   </PIN>
   <PIN pinname="Input 3" visible="1">
   </PIN>
   <PIN pinname="Switch" visible="1">
   </PIN>
   </NODE>
   <LINK srcnodeid="238" srcpinname="Output" dstnodeid="268" dstpinname="Input 2">
   </LINK>
   <LINK srcnodeid="267" srcpinname="OnChange" dstnodeid="268" dstpinname="Input 1">
   </LINK>
   <LINK srcnodeid="251" srcpinname="Output" dstnodeid="68" dstpinname="XYZ">
   </LINK>
   <NODE systemname="Switch (Value Input)" nodename="Switch (Value Input)" componentmode="Hidden" id="270">
   <BOUNDS type="Node" left="9060" top="2415" width="100" height="100">
   </BOUNDS>
   <PIN pinname="Input Count" slicecount="1" values="5">
   </PIN>
   <PIN pinname="Input 1" visible="1" slicecount="1" values="4">
   </PIN>
   <PIN pinname="Input 2" visible="1" slicecount="1" values="8">
   </PIN>
   <PIN pinname="Input 3" visible="1" slicecount="1" values="16">
   </PIN>
   <PIN pinname="Input 4" visible="1" slicecount="1" values="32">
   </PIN>
   <PIN pinname="Input 5" visible="1" slicecount="1" values="64">
   </PIN>
   <PIN pinname="Output" visible="1">
   </PIN>
   <PIN pinname="Switch" visible="1" slicecount="1" values="0">
   </PIN>
   </NODE>
   <LINK srcnodeid="270" srcpinname="Output" dstnodeid="264" dstpinname="Beat Type">
   </LINK>
   <NODE systemname="GetSlice (Spreads)" nodename="GetSlice (Spreads)" componentmode="Hidden" id="271">
   <BOUNDS type="Node" left="2415" top="5940" width="100" height="100">
   </BOUNDS>
   <PIN pinname="Input" visible="1">
   </PIN>
   <PIN pinname="Index" slicecount="1" values="8">
   </PIN>
   <PIN pinname="Output" visible="1">
   </PIN>
   </NODE>
   <NODE systemname="OR (Boolean)" nodename="OR (Boolean)" componentmode="Hidden" id="272">
   <BOUNDS type="Node" left="2580" top="3840" width="100" height="100">
   </BOUNDS>
   <PIN pinname="Output" visible="1">
   </PIN>
   <PIN pinname="Input 1" visible="1" slicecount="1" values="0">
   </PIN>
   <PIN pinname="Input 2" visible="1">
   </PIN>
   </NODE>
   <LINK srcnodeid="116" srcpinname="Y Output Value" dstnodeid="153" dstpinname="Send">
   </LINK>
   <LINK srcnodeid="272" srcpinname="Output" dstnodeid="116" dstpinname="Y Input Value">
   </LINK>
   <NODE systemname="IOBox (Value Advanced)" nodename="IOBox (Value Advanced)" componentmode="InABox" id="275">
   <BOUNDS type="Node" left="15" top="1125" width="100" height="100">
   </BOUNDS>
   <BOUNDS type="Box" left="15" top="1125" width="480" height="480">
   </BOUNDS>
   <PIN pinname="Value Type" slicecount="1" values="Boolean">
   </PIN>
   <PIN pinname="Behavior" slicecount="1" values="Bang">
   </PIN>
   <PIN pinname="Y Output Value" visible="1">
   </PIN>
   <PIN pinname="Descriptive Name" slicecount="1" values="Clear">
   </PIN>
   </NODE>
   <LINK srcnodeid="275" srcpinname="Y Output Value" dstnodeid="272" dstpinname="Input 1">
   </LINK>
   <NODE systemname="TogEdge (Animation)" nodename="TogEdge (Animation)" componentmode="Hidden" id="276">
   <BOUNDS type="Node" left="2475" top="6435" width="100" height="100">
   </BOUNDS>
   <PIN pinname="Input" visible="1">
   </PIN>
   <PIN pinname="Up Edge" visible="1">
   </PIN>
   </NODE>
   <LINK srcnodeid="271" srcpinname="Output" dstnodeid="276" dstpinname="Input">
   </LINK>
   <LINK srcnodeid="276" srcpinname="Up Edge" dstnodeid="272" dstpinname="Input 2">
   </LINK>
   <NODE systemname="LFO (Animation)" nodename="LFO (Animation)" componentmode="Hidden" id="278">
   <BOUNDS type="Node" left="9810" top="930" width="100" height="100">
   </BOUNDS>
   <PIN pinname="Change" visible="1">
   </PIN>
   </NODE>
   <LINK srcnodeid="278" srcpinname="Change" dstnodeid="268" dstpinname="Input 3">
   </LINK>
   <NODE nodename="IOBox (Value Advanced)" componentmode="InABox" id="279" systemname="IOBox (Value Advanced)">
   <BOUNDS type="Box" left="10110" top="315" width="795" height="240">
   </BOUNDS>
   <BOUNDS type="Node" left="10110" top="315" width="0" height="0">
   </BOUNDS>
   <PIN pinname="Y Input Value" slicecount="1" values="1">
   </PIN>
   <PIN pinname="Units" slicecount="1" values="s">
   </PIN>
   <PIN pinname="Precision" slicecount="1" values="4">
   </PIN>
   <PIN pinname="Descriptive Name" slicecount="1" values="Period">
   </PIN>
   </NODE>
   <LINK srcnodeid="279" srcpinname="Y Output Value" dstnodeid="278" dstpinname="Period">
   </LINK>
   <NODE systemname="IOBox (Value Advanced)" nodename="IOBox (Value Advanced)" componentmode="InABox" id="280">
   <BOUNDS type="Node" left="2430" top="660" width="100" height="100">
   </BOUNDS>
   <BOUNDS type="Box" left="2430" top="660" width="795" height="240">
   </BOUNDS>
   <PIN pinname="Y Output Value" visible="1">
   </PIN>
   <PIN pinname="Y Input Value" slicecount="1" values="2">
   </PIN>
   <PIN pinname="Descriptive Name" slicecount="1" values="|Sync OSC/MIDI/LFO|">
   </PIN>
   </NODE>
   <LINK srcnodeid="280" srcpinname="Y Output Value" dstnodeid="268" dstpinname="Switch">
   </LINK>
   <LINK srcnodeid="132" srcpinname="Output" dstnodeid="271" dstpinname="Input">
   </LINK>
   <NODE systemname="Sequenze-1" filename="Sequenze-1.v4p" nodename="Sequenze-1.v4p" componentmode="InAWindow" id="285">
   <BOUNDS type="Node" left="12093" top="7451" width="0" height="0">
   </BOUNDS>
   <BOUNDS type="Box" left="3021" top="1864" width="18145" height="11175">
   </BOUNDS>
   <BOUNDS type="Window" left="6090" top="2355" width="18150" height="11175">
   </BOUNDS>
   </NODE>
   <LINK srcnodeid="268" srcpinname="Output" dstnodeid="285" dstpinname="Up">
   </LINK>
   <LINK srcnodeid="132" srcpinname="Output" dstnodeid="285" dstpinname="Grid Input">
   </LINK>
   <LINK srcnodeid="116" srcpinname="Y Output Value" dstnodeid="285" dstpinname="Reset">
   </LINK>
   <LINK srcnodeid="151" srcpinname="Y Output Value" dstnodeid="285" dstpinname="Input 2">
   </LINK>
   <LINK srcnodeid="100" srcpinname="Y Output Value" dstnodeid="285" dstpinname="Count">
   </LINK>
   <LINK srcnodeid="285" srcpinname="Transport Timing" dstnodeid="270" dstpinname="Switch">
   </LINK>
   <LINK srcnodeid="285" srcpinname="Transport Timing" dstnodeid="238" dstpinname="Switch">
   </LINK>
   <LINK srcnodeid="135" srcpinname="Output" dstnodeid="285" dstpinname="Input 1">
   </LINK>
   <LINK srcnodeid="254" srcpinname="Y Output Value" dstnodeid="285" dstpinname="Channel">
   </LINK>
   <LINK srcnodeid="253" srcpinname="Output Enum" dstnodeid="285" dstpinname="Midi Output Port">
   </LINK>
   <LINK srcnodeid="285" srcpinname="Output 1" dstnodeid="90" dstpinname="Y Input Value">
   </LINK>
   <LINK srcnodeid="91" srcpinname="Y Output Value" dstnodeid="285" dstpinname="Spread">
   </LINK>
   </PATCH>